{
  "schemaVersion": 1,
  "featureId": "feat_library_29524f2717",
  "title": "Node source packages/shared/src/schemas#1",
  "summary": "Node/TypeScript source group packages/shared/src/schemas#1 with 12 files.",
  "kind": "library",
  "source": "node-source-group",
  "confidence": "medium",
  "entrypoints": [
    {
      "path": "packages/shared/package.json",
      "symbol": "packages/shared/src/schemas#1",
      "route": null,
      "command": null
    }
  ],
  "ownedFiles": [
    {
      "path": "packages/shared/src/schemas/auth.ts",
      "reason": "source group packages/shared/src/schemas#1"
    },
    {
      "path": "packages/shared/src/schemas/bulk-import.ts",
      "reason": "source group packages/shared/src/schemas#1"
    },
    {
      "path": "packages/shared/src/schemas/bulk-jobs.ts",
      "reason": "source group packages/shared/src/schemas#1"
    },
    {
      "path": "packages/shared/src/schemas/bulk-notifications.ts",
      "reason": "source group packages/shared/src/schemas#1"
    },
    {
      "path": "packages/shared/src/schemas/bulk-operations.ts",
      "reason": "source group packages/shared/src/schemas#1"
    },
    {
      "path": "packages/shared/src/schemas/bulk-ops.ts",
      "reason": "source group packages/shared/src/schemas#1"
    },
    {
      "path": "packages/shared/src/schemas/calendar.ts",
      "reason": "source group packages/shared/src/schemas#1"
    },
    {
      "path": "packages/shared/src/schemas/media.ts",
      "reason": "source group packages/shared/src/schemas#1"
    },
    {
      "path": "packages/shared/src/schemas/notifications.ts",
      "reason": "source group packages/shared/src/schemas#1"
    },
    {
      "path": "packages/shared/src/schemas/oauth.ts",
      "reason": "source group packages/shared/src/schemas#1"
    },
    {
      "path": "packages/shared/src/schemas/post-history.ts",
      "reason": "source group packages/shared/src/schemas#1"
    },
    {
      "path": "packages/shared/src/schemas/posts.ts",
      "reason": "source group packages/shared/src/schemas#1"
    }
  ],
  "contextFiles": [
    {
      "path": "packages/shared/package.json",
      "reason": "package manifest"
    },
    {
      "path": "packages/shared/src/schemas/__tests__/bulk-schemas.test.ts",
      "reason": "associated test"
    }
  ],
  "tests": [
    {
      "path": "packages/shared/src/schemas/__tests__/bulk-schemas.test.ts",
      "command": "pnpm --dir packages/shared test"
    }
  ],
  "tags": [
    "node",
    "typescript",
    "source-group",
    "project:@sms/shared",
    "project-root:packages/shared"
  ],
  "trustBoundaries": [],
  "status": "pending",
  "lock": null,
  "findingIds": [],
  "patchAttemptIds": [],
  "analysisHistory": [],
  "createdAt": "2026-05-18T23:00:06.938Z",
  "updatedAt": "2026-05-18T23:00:06.938Z"
}
