{"schemaVersion":1,"featureId":"feat_ui-flow_8f29c31874","title":"React component Sidebar","summary":"React component implemented by packages/web/src/components/layout/Sidebar.tsx.","kind":"ui-flow","source":"react-component","confidence":"medium","entrypoints":[{"path":"packages/web/src/components/layout/Sidebar.tsx","symbol":"Sidebar","route":null,"command":null}],"ownedFiles":[{"path":"packages/web/src/components/layout/Sidebar.tsx","reason":"component implementation"}],"contextFiles":[{"path":"packages/web/package.json","reason":"package manifest"},{"path":"packages/web/src/components/layout/__tests__/NotificationBell.test.tsx","reason":"associated test"}],"tests":[{"path":"packages/web/src/components/layout/__tests__/NotificationBell.test.tsx","command":"pnpm --dir packages/web test"}],"tags":["react","component","web"],"trustBoundaries":["user-input","network","serialization"],"status":"pending","lock":null,"findingIds":[],"patchAttemptIds":[],"analysisHistory":[],"createdAt":"2026-05-18T23:00:06.938Z","updatedAt":"2026-05-18T23:00:06.938Z"}
